plmini/__init__.py
plmini/client.py
plmini/dispatcher.py
plmini/driver.py
plmini/pb/__init__.py
plmini/pb/plmini_pb2.py
plmini/pb/plmini_pb2_grpc.py
plmini-0.0.10.dist-info/WHEEL
plmini-0.0.10.dist-info/METADATA
plmini-0.0.10.dist-info/RECORD
