Metadata-Version: 2.1
Name: plmini
Version: 0.0.10
Summary: Prototyping Lab Mini Development Library
License: MIT
Author: Kotone Itaya
Author-email: kotone@sfc.keio.ac.jp
Requires-Python: >=3.5,<4.0
Classifier: License :: OSI Approved :: MIT License
Classifier: Programming Language :: Python :: 3
Classifier: Programming Language :: Python :: 3.5
Classifier: Programming Language :: Python :: 3.6
Classifier: Programming Language :: Python :: 3.7
Classifier: Programming Language :: Python :: 3.8
Classifier: Programming Language :: Python :: 3.9
Requires-Dist: grpcio (>=1.36.1,<2.0.0)
Requires-Dist: jsonschema (>=3.2.0,<4.0.0)
Requires-Dist: protobuf (>=3.15.6,<4.0.0)
